<?xml version="1.0" encoding="utf-8" ?>
<dwsync>
<file name="DataTable.Class.php" server="catbsc1//dwdm-fileupload/" local="130221828000000000" remote="130221828000000000" />
<file name="ReadDir.Class.php" server="catbsc1//dwdm-fileupload/" local="130221828000000000" remote="130221828000000000" />
<file name="Sendmail.Class.php" server="catbsc1//dwdm-fileupload/" local="130221828000000000" remote="130221828000000000" />
<file name="Auth.Class.php" server="10.32.13.45//dwdm-management/" local="130533732000000000" remote="130533732000000000" />
<file name="DataTable.Class.php" server="10.32.13.45//dwdm-management/" local="130800170175358666" remote="130800168600000000" />
<file name="Main.Class.php" server="10.32.13.45//dwdm-management/" local="130533732000000000" remote="130533732000000000" />
<file name="ReadDir.Class.php" server="10.32.13.45//dwdm-management/" local="130967002800000000" remote="130967002800000000" />
<file name="Sendmail.Class.php" server="10.32.13.45//dwdm-management/" local="130533732000000000" remote="130533732000000000" />
<file name="Form.Class.php" server="10.32.13.45//dwdm-management/" local="130533732000000000" remote="130533732000000000" />
</dwsync>